runx/__init__.py
runx/_version.py
runx/collections.py
runx/config.py
runx/farm.py
runx/logx.py
runx/runx.py
runx/sumx.py
runx/utils.py
runx-0.0.11.dist-info/LICENSE
runx-0.0.11.dist-info/METADATA
runx-0.0.11.dist-info/WHEEL
runx-0.0.11.dist-info/top_level.txt
runx-0.0.11.dist-info/RECORD
