Metadata-Version: 2.1
Name: runx
Version: 0.0.11
Summary: runx - experiment manager for machine learning research
Home-page: https://github.com/NVIDIA/runx
Author: Andrew Tao
Author-email: atao@nvidia.com
License: UNKNOWN
Platform: UNKNOWN
Classifier: Programming Language :: Python :: 3
Classifier: License :: OSI Approved :: MIT License
Classifier: Operating System :: OS Independent
Requires-Python: >=3.6
Requires-Dist: pyyaml (>=5.1.1)
Requires-Dist: coolname (>=1.1.0)
Requires-Dist: tabulate (>=0.8.3)
Requires-Dist: tensorboardX (>=1.4)
